{
  "_class": "shapePath",
  "booleanOperation": -1,
  "do_objectID": "4D6CD08E-8FF1-4B0F-8207-09FADF977E7F",
  "edited": true,
  "exportOptions": {
    "_class": "exportOptions",
    "exportFormats": [
    ],
    "includedLayerIds": [
    ],
    "layerOptions": 0,
    "shouldTrim": false
  },
  "frame": {
    "_class": "rect",
    "constrainProportions": false,
    "do_objectID": "DA1D0328-42C3-46D5-9029-52D7B49C2D9C",
    "height": 9,
    "width": 9,
    "x": 24,
    "y": 24
  },
  "isFlippedHorizontal": false,
  "isFlippedVertical": false,
  "isLocked": false,
  "isVisible": true,
  "layerListExpandedType": 0,
  "name": "Path",
  "nameIsFixed": false,
  "path": {
    "_class": "path",
    "do_objectID": "9C005B39-F632-47B8-98C5-9E9F4A3B24A0",
    "isClosed": true,
    "pointRadiusBehaviour": 0,
    "points": [
      {
        "_class": "curvePoint",
        "cornerRadius": 0,
        "curveFrom": "{1, 0.16666666666666666}",
        "curveMode": 1,
        "curveTo": "{1, 0.16666666666666666}",
        "do_objectID": "9E89A8EC-D1A7-446F-9ED2-A8B04E6EFE7A",
        "hasCurveFrom": false,
        "hasCurveTo": false,
        "point": "{1, 0.16666666666666666}"
      },
      {
        "_class": "curvePoint",
        "cornerRadius": 0,
        "curveFrom": "{1, 0.88000000000000811}",
        "curveMode": 4,
        "curveTo": "{1, 0.83333333333333337}",
        "do_objectID": "EF0A2C76-8C8E-4FFC-BBF4-BF25171952DC",
        "hasCurveFrom": true,
        "hasCurveTo": false,
        "point": "{1, 0.83333333333333337}"
      },
      {
        "_class": "curvePoint",
        "cornerRadius": 0,
        "curveFrom": "{0.91944444444444196, 0.98388888888889092}",
        "curveMode": 2,
        "curveTo": "{0.98388888888889092, 0.9194444444444545}",
        "do_objectID": "723F0615-D036-4528-ACB5-61C8F9877DDA",
        "hasCurveFrom": true,
        "hasCurveTo": true,
        "point": "{0.95177777777778116, 0.95166666666667277}"
      },
      {
        "_class": "curvePoint",
        "cornerRadius": 0,
        "curveFrom": "{0.83333333333333337, 1}",
        "curveMode": 4,
        "curveTo": "{0.88000000000000811, 1}",
        "do_objectID": "12620A05-95B2-4873-9DF0-9933A6333FD1",
        "hasCurveFrom": false,
        "hasCurveTo": true,
        "point": "{0.83333333333333337, 1}"
      },
      {
        "_class": "curvePoint",
        "cornerRadius": 0,
        "curveFrom": "{0.12000000000000455, 1}",
        "curveMode": 4,
        "curveTo": "{0.16666666666666666, 1}",
        "do_objectID": "1BA2F000-F340-4012-84AB-6C9ECDBABD22",
        "hasCurveFrom": true,
        "hasCurveTo": false,
        "point": "{0.16666666666666666, 1}"
      },
      {
        "_class": "curvePoint",
        "cornerRadius": 0,
        "curveFrom": "{0.016111111111109092, 0.9194444444444545}",
        "curveMode": 2,
        "curveTo": "{0.080555555555558087, 0.98388888888889092}",
        "do_objectID": "C64C5643-55E6-4937-9BB5-66CF87D7D2B1",
        "hasCurveFrom": true,
        "hasCurveTo": true,
        "point": "{0.048333333333339903, 0.95166666666667277}"
      },
      {
        "_class": "curvePoint",
        "cornerRadius": 0,
        "curveFrom": "{0, 0.83333333333333337}",
        "curveMode": 4,
        "curveTo": "{0, 0.88000000000000811}",
        "do_objectID": "A6F6D29A-7469-4574-97B2-2A9689873B73",
        "hasCurveFrom": false,
        "hasCurveTo": true,
        "point": "{0, 0.83333333333333337}"
      },
      {
        "_class": "curvePoint",
        "cornerRadius": 0,
        "curveFrom": "{0, 0.12000000000001718}",
        "curveMode": 4,
        "curveTo": "{0, 0.16666666666666666}",
        "do_objectID": "CC87ED48-314D-423F-A8AF-67465FE91C3B",
        "hasCurveFrom": true,
        "hasCurveTo": false,
        "point": "{0, 0.16666666666666666}"
      },
      {
        "_class": "curvePoint",
        "cornerRadius": 0,
        "curveFrom": "{0.080555555555558087, 0.016222222222242837}",
        "curveMode": 2,
        "curveTo": "{0.016111111111109092, 0.080555555555570715}",
        "do_objectID": "1F6E50B0-52A4-48AD-926B-28BCF756132A",
        "hasCurveFrom": true,
        "hasCurveTo": true,
        "point": "{0.048333333333339903, 0.048333333333352532}"
      },
      {
        "_class": "curvePoint",
        "cornerRadius": 0,
        "curveFrom": "{0.16666666666666666, 0}",
        "curveMode": 4,
        "curveTo": "{0.12000000000000455, 0}",
        "do_objectID": "17380043-BBF3-431E-94FD-8CB7B5FE383F",
        "hasCurveFrom": false,
        "hasCurveTo": true,
        "point": "{0.16666666666666666, 0}"
      },
      {
        "_class": "curvePoint",
        "cornerRadius": 0,
        "curveFrom": "{0.88000000000000811, 0}",
        "curveMode": 4,
        "curveTo": "{0.83333333333333337, 0}",
        "do_objectID": "D25D2A3F-4EB1-4AD9-95DB-F279169EF3BA",
        "hasCurveFrom": true,
        "hasCurveTo": false,
        "point": "{0.83333333333333337, 0}"
      },
      {
        "_class": "curvePoint",
        "cornerRadius": 0,
        "curveFrom": "{0.98388888888889092, 0.080555555555570715}",
        "curveMode": 2,
        "curveTo": "{0.91944444444444196, 0.016222222222242837}",
        "do_objectID": "6E084E9F-7D94-4819-9325-831849E3398D",
        "hasCurveFrom": true,
        "hasCurveTo": true,
        "point": "{0.95177777777778116, 0.048333333333352532}"
      },
      {
        "_class": "curvePoint",
        "cornerRadius": 0,
        "curveFrom": "{1, 0.16666666666666666}",
        "curveMode": 4,
        "curveTo": "{1, 0.12000000000001718}",
        "do_objectID": "516CD5FB-C6BD-4AFC-B1C4-64647B36C9A2",
        "hasCurveFrom": false,
        "hasCurveTo": true,
        "point": "{1, 0.16666666666666666}"
      }
    ]
  },
  "resizingConstraint": 63,
  "resizingType": 0,
  "rotation": 0,
  "shouldBreakMaskChain": false
}