{
  "_class": "rectangle",
  "booleanOperation": -1,
  "do_objectID": "9EC68942-C9F3-4482-A68E-AF266F77F7E7",
  "edited": false,
  "exportOptions": {
    "_class": "exportOptions",
    "exportFormats": [
    ],
    "includedLayerIds": [
    ],
    "layerOptions": 0,
    "shouldTrim": false
  },
  "fixedRadius": 3,
  "frame": {
    "_class": "rect",
    "constrainProportions": false,
    "do_objectID": "D2D4DCD3-27C5-4AE6-91F0-E8A7875DDD4B",
    "height": 28,
    "width": 250,
    "x": 0,
    "y": 0
  },
  "hasConvertedToNewRoundCorners": true,
  "isFlippedHorizontal": false,
  "isFlippedVertical": false,
  "isLocked": false,
  "isVisible": true,
  "layerListExpandedType": 0,
  "name": "Path",
  "nameIsFixed": false,
  "path": {
    "_class": "path",
    "do_objectID": "26FE9163-172E-4A13-9EAD-5E081C20901B",
    "isClosed": true,
    "pointRadiusBehaviour": 0,
    "points": [
      {
        "_class": "curvePoint",
        "cornerRadius": 3,
        "curveFrom": "{0, 0}",
        "curveMode": 1,
        "curveTo": "{0, 0}",
        "do_objectID": "F68D5B5A-0FC2-4695-A5A8-66FF67E915E9",
        "hasCurveFrom": false,
        "hasCurveTo": false,
        "point": "{0, 0}"
      },
      {
        "_class": "curvePoint",
        "cornerRadius": 3,
        "curveFrom": "{0, 1}",
        "curveMode": 1,
        "curveTo": "{0, 1}",
        "do_objectID": "147F8411-500E-47B5-AEBE-42E592308FA7",
        "hasCurveFrom": false,
        "hasCurveTo": false,
        "point": "{0, 1}"
      },
      {
        "_class": "curvePoint",
        "cornerRadius": 3,
        "curveFrom": "{1, 1}",
        "curveMode": 1,
        "curveTo": "{1, 1}",
        "do_objectID": "88834264-F7FC-409E-BD8A-6FD351D185DC",
        "hasCurveFrom": false,
        "hasCurveTo": false,
        "point": "{1, 1}"
      },
      {
        "_class": "curvePoint",
        "cornerRadius": 3,
        "curveFrom": "{1, 0}",
        "curveMode": 1,
        "curveTo": "{1, 0}",
        "do_objectID": "35A4C876-804A-4F06-A96F-77BFA6EFB1C3",
        "hasCurveFrom": false,
        "hasCurveTo": false,
        "point": "{1, 0}"
      }
    ]
  },
  "resizingConstraint": 63,
  "resizingType": 0,
  "rotation": 0,
  "shouldBreakMaskChain": false
}