{
  "_class": "shapeGroup",
  "clippingMaskMode": 0,
  "do_objectID": "3DA0E3AD-26B7-4D15-8E3F-F4E735A67DE8",
  "exportOptions": {
    "_class": "exportOptions",
    "exportFormats": [
    ],
    "includedLayerIds": [
    ],
    "layerOptions": 0,
    "shouldTrim": false
  },
  "frame": {
    "_class": "rect",
    "constrainProportions": false,
    "do_objectID": "FE4E5BE2-FBE6-45AD-B499-8433631FAD28",
    "height": 35.84999999999997,
    "width": 35.84899999999993,
    "x": 648.594,
    "y": 720.771
  },
  "hasClickThrough": false,
  "hasClippingMask": false,
  "isFlippedHorizontal": false,
  "isFlippedVertical": false,
  "isLocked": false,
  "isVisible": true,
  "layerListExpandedType": 0,
  "layers": [
    {
      "class": "shapePath",
      "id": "9FFD1E77-9D82-4674-AEFD-BAE08265B91B"
    },
    {
      "class": "shapePath",
      "id": "AFF2D063-FC27-456F-8113-89EE3A6D1FCB"
    }
  ],
  "name": "Fill 129",
  "nameIsFixed": false,
  "resizingConstraint": 63,
  "resizingType": 0,
  "rotation": 0,
  "shouldBreakMaskChain": false,
  "style": {
    "_class": "style",
    "borders": [
      {
        "_class": "border",
        "color": {
          "_class": "color",
          "alpha": 1,
          "blue": 0.592,
          "green": 0.592,
          "red": 0.592
        },
        "do_objectID": "712EAEB4-0007-45C4-B147-8FB4555E8745",
        "fillType": 0,
        "isEnabled": false,
        "position": 0,
        "thickness": 1
      }
    ],
    "do_objectID": "C0F3FB3C-226B-4CB7-8700-1ABAE06A3D34",
    "endDecorationType": 0,
    "fills": [
      {
        "_class": "fill",
        "color": {
          "_class": "color",
          "alpha": 1,
          "blue": 0.125,
          "green": 0.122,
          "red": 0.137
        },
        "do_objectID": "D5C99A76-B1DE-4696-B5A5-6049F47F4F12",
        "fillType": 0,
        "isEnabled": true,
        "noiseIndex": 0,
        "noiseIntensity": 0,
        "patternFillType": 0,
        "patternTileScale": 1
      }
    ],
    "miterLimit": 10,
    "startDecorationType": 0
  },
  "windingRule": 1
}