{
  "_class": "shapeGroup",
  "clippingMaskMode": 0,
  "do_objectID": "DA9CE682-EAF8-40E3-BD7A-4EB14E4D3440",
  "exportOptions": {
    "_class": "exportOptions",
    "exportFormats": [
    ],
    "includedLayerIds": [
    ],
    "layerOptions": 0,
    "shouldTrim": false
  },
  "frame": {
    "_class": "rect",
    "constrainProportions": false,
    "do_objectID": "39B0A2CA-473F-47D9-97D6-06A0B6AFF552",
    "height": 32,
    "width": 102,
    "x": 488,
    "y": 1
  },
  "hasClickThrough": false,
  "hasClippingMask": false,
  "isFlippedHorizontal": false,
  "isFlippedVertical": false,
  "isLocked": false,
  "isVisible": true,
  "layerListExpandedType": 0,
  "layers": [
    {
      "class": "rectangle",
      "id": "641CC676-EB36-43DA-BFB0-BA830359C612"
    }
  ],
  "name": "Rectangle 28",
  "nameIsFixed": false,
  "resizingConstraint": 63,
  "resizingType": 0,
  "rotation": 0,
  "shouldBreakMaskChain": false,
  "style": {
    "_class": "style",
    "borders": [
      {
        "_class": "border",
        "color": {
          "_class": "color",
          "alpha": 1,
          "blue": 0.2117647058823529,
          "green": 0.6352941176470589,
          "red": 0.9333333333333333
        },
        "do_objectID": "CADCB95F-5B91-40A4-B1B9-CF3F28D4566A",
        "fillType": 0,
        "isEnabled": true,
        "position": 2,
        "thickness": 1
      }
    ],
    "do_objectID": "4ABE42A7-9DFB-482C-9785-6DB4E2E35FC2",
    "endDecorationType": 0,
    "fills": [
      {
        "_class": "fill",
        "color": {
          "_class": "color",
          "alpha": 1,
          "blue": 0.3058823529411765,
          "green": 0.6784313725490198,
          "red": 0.9411764705882353
        },
        "do_objectID": "7D2C7F19-241B-4C36-9E43-FD1EBC3A5DD2",
        "fillType": 0,
        "isEnabled": true,
        "noiseIndex": 0,
        "noiseIntensity": 0,
        "patternFillType": 0,
        "patternTileScale": 1
      }
    ],
    "miterLimit": 10,
    "startDecorationType": 0
  },
  "windingRule": 1
}