{
  "_class": "shapeGroup",
  "clippingMaskMode": 0,
  "do_objectID": "1D1EF178-5FA1-4F54-B679-42622EECD2ED",
  "exportOptions": {
    "_class": "exportOptions",
    "exportFormats": [
    ],
    "includedLayerIds": [
    ],
    "layerOptions": 0,
    "shouldTrim": false
  },
  "frame": {
    "_class": "rect",
    "constrainProportions": false,
    "do_objectID": "5486A0BB-5A1D-410E-89DC-A65B01E660EA",
    "height": 14,
    "width": 14,
    "x": 19,
    "y": 19
  },
  "hasClickThrough": false,
  "hasClippingMask": false,
  "isFlippedHorizontal": false,
  "isFlippedVertical": false,
  "isLocked": false,
  "isVisible": true,
  "layerListExpandedType": 0,
  "layers": [
    {
      "class": "rectangle",
      "id": "6574402A-7682-4EB9-92D9-09DA6C59B7F7"
    }
  ],
  "name": "Rectangle 33",
  "nameIsFixed": false,
  "resizingConstraint": 63,
  "resizingType": 0,
  "rotation": 0,
  "shouldBreakMaskChain": false,
  "style": {
    "_class": "style",
    "borders": [
      {
        "_class": "border",
        "color": {
          "_class": "color",
          "alpha": 1,
          "blue": 0.8,
          "green": 0.8,
          "red": 0.8
        },
        "do_objectID": "4C4EB282-A606-42C8-94EC-0E7A1D8F796E",
        "fillType": 0,
        "isEnabled": true,
        "position": 2,
        "thickness": 1
      }
    ],
    "do_objectID": "CBCAF104-384C-4E82-89D4-48342E9D0F2C",
    "endDecorationType": 0,
    "fills": [
      {
        "_class": "fill",
        "color": {
          "_class": "color",
          "alpha": 1,
          "blue": 0.847,
          "green": 0.847,
          "red": 0.847
        },
        "do_objectID": "7A766DA4-AA8E-4525-9B36-9F279801E485",
        "fillType": 0,
        "isEnabled": false,
        "noiseIndex": 0,
        "noiseIntensity": 0,
        "patternFillType": 0,
        "patternTileScale": 1
      }
    ],
    "miterLimit": 10,
    "startDecorationType": 0
  },
  "windingRule": 1
}